Workbook

Sheet Dashboard
A1: KDP CATALOG TRACKER · 20 Categories × 10 Books = 200 Titles
A2: Titles are pre-loaded in the Catalog tab. Set each book's Status as you write — this dashboard updates itself. Green = shipped.
A4: Published: | B4: =COUNTIF(Catalog!$F$2:$F$201,"Published") -> 0 | C4: of 200 | D4: In progress: | E4: =200-COUNTIF(Catalog!$F$2:$F$201,"Idea")-COUNTIF(Catalog!$F$2:$F$201,"Published") -> 0 | F4: Not started: | G4: =COUNTIF(Catalog!$F$2:$F$201,"Idea") -> 200 | H4: Overall: | I4: =COUNTIF(Catalog!$F$2:$F$201,"Published")/200 -> 0
A6: Category | B6: Division | C6: Effort | D6: Done | E6: In Prog. | F6: To Do | G6: Progress | H6: Why It Sells | I6: BSR of Top Titles | J6: Reviews = crowded above | K6: Production Tip
A7: Contemporary & Small-Town Romance | B7: Fiction | C7: High | D7: =COUNTIFS(Catalog!$A$2:$A$201,$A7,Catalog!$F$2:$F$201,"Published") -> 0 | E7: =10-COUNTIFS(Catalog!$A$2:$A$201,$A7,Catalog!$F$2:$F$201,"Idea")-D7 -> 0 | F7: =COUNTIFS(Catalog!$A$2:$A$201,$A7,Catalog!$F$2:$F$201,"Idea") -> 10 | G7: =D7/10 -> 0 | H7: Romance readers buy 3–5 books/month; series read-through compounds royalties. | I7: Sub-niche leaders often top ~20k | J7: 200–1,000+ | K7: KU + $4.99; lean on tropes (enemies-to-lovers, fake dating).
A8: Romantasy | B8: Fiction | C8: High | D8: =COUNTIFS(Catalog!$A$2:$A$201,$A8,Catalog!$F$2:$F$201,"Published") -> 0 | E8: =10-COUNTIFS(Catalog!$A$2:$A$201,$A8,Catalog!$F$2:$F$201,"Idea")-D8 -> 0 | F8: =COUNTIFS(Catalog!$A$2:$A$201,$A8,Catalog!$F$2:$F$201,"Idea") -> 10 | G8: =D8/10 -> 0 | H8: Outsells traditional fantasy ~3:1; BookTok-driven; readers accept $9.99–14.99. | I8: Hot — leaders under 3k | J8: High (500+) | K8: Fourth Wing lane; longer novels, collector/special-edition culture.
A9: Dark & Sports Romance | B9: Fiction | C9: High | D9: =COUNTIFS(Catalog!$A$2:$A$201,$A9,Catalog!$F$2:$F$201,"Published") -> 0 | E9: =10-COUNTIFS(Catalog!$A$2:$A$201,$A9,Catalog!$F$2:$F$201,"Idea")-D9 -> 0 | F9: =COUNTIFS(Catalog!$A$2:$A$201,$A9,Catalog!$F$2:$F$201,"Idea") -> 10 | G9: =D9/10 -> 0 | H9: #DarkRomance ~4.2B views; morally-gray heroes; heavy repeat buying. | I9: Competitive | J9: High | K9: High-heat tropes drive viral discovery.
A10: Psychological Thrillers | B10: Fiction | C10: High | D10: =COUNTIFS(Catalog!$A$2:$A$201,$A10,Catalog!$F$2:$F$201,"Published") -> 0 | E10: =10-COUNTIFS(Catalog!$A$2:$A$201,$A10,Catalog!$F$2:$F$201,"Idea")-D10 -> 0 | F10: =COUNTIFS(Catalog!$A$2:$A$201,$A10,Catalog!$F$2:$F$201,"Idea") -> 10 | G10: =D10/10 -> 0 | H10: Dominate Kindle Unlimited 'Most Read'; twist-driven bingeing. | I10: Competitive | J10: High | K10: Spoiler-free twist reveals hook well on TikTok.
A11: Cozy Mysteries | B11: Fiction | C11: Medium–High | D11: =COUNTIFS(Catalog!$A$2:$A$201,$A11,Catalog!$F$2:$F$201,"Published") -> 0 | E11: =10-COUNTIFS(Catalog!$A$2:$A$201,$A11,Catalog!$F$2:$F$201,"Idea")-D11 -> 0 | F11: =COUNTIFS(Catalog!$A$2:$A$201,$A11,Catalog!$F$2:$F$201,"Idea") -> 10 | G11: =D11/10 -> 0 | H11: Growing; high series-completion; seasonal Q4 'cozy' peak. | I11: Moderate | J11: 100–500 | K11: Build a series around one setting/sleuth.
A12: Sci-Fi & Fantasy | B12: Fiction | C12: High | D12: =COUNTIFS(Catalog!$A$2:$A$201,$A12,Catalog!$F$2:$F$201,"Published") -> 0 | E12: =10-COUNTIFS(Catalog!$A$2:$A$201,$A12,Catalog!$F$2:$F$201,"Idea")-D12 -> 0 | F12: =COUNTIFS(Catalog!$A$2:$A$201,$A12,Catalog!$F$2:$F$201,"Idea") -> 10 | G12: =D12/10 -> 0 | H12: Binge/series backbone of self-publishing; strong read-through. | I12: Varies by sub-genre | J12: Varies | K12: One release lifts the whole backlist.
A13: Puzzle Books | B13: Low-Content | C13: Low | D13: =COUNTIFS(Catalog!$A$2:$A$201,$A13,Catalog!$F$2:$F$201,"Published") -> 0 | E13: =10-COUNTIFS(Catalog!$A$2:$A$201,$A13,Catalog!$F$2:$F$201,"Idea")-D13 -> 0 | F13: =COUNTIFS(Catalog!$A$2:$A$201,$A13,Catalog!$F$2:$F$201,"Idea") -> 10 | G13: =D13/10 -> 0 | H13: Strongest low-content performer; evergreen plus seasonal spikes. | I13: 5k–50k in sub-niche | J13: 50–300 | K13: Niche down (themed sudoku, topic word-search).
A14: Coloring Books | B14: Low-Content | C14: Low | D14: =COUNTIFS(Catalog!$A$2:$A$201,$A14,Catalog!$F$2:$F$201,"Published") -> 0 | E14: =10-COUNTIFS(Catalog!$A$2:$A$201,$A14,Catalog!$F$2:$F$201,"Idea")-D14 -> 0 | F14: =COUNTIFS(Catalog!$A$2:$A$201,$A14,Catalog!$F$2:$F$201,"Idea") -> 10 | G14: =D14/10 -> 0 | H14: Specialty coloring ranks high; strong gift market. | I14: 5k–50k | J14: 50–300 | K14: Specific theme + specific audience beats generic.
A15: Prompted Journals | B15: Low-Content | C15: Low | D15: =COUNTIFS(Catalog!$A$2:$A$201,$A15,Catalog!$F$2:$F$201,"Published") -> 0 | E15: =10-COUNTIFS(Catalog!$A$2:$A$201,$A15,Catalog!$F$2:$F$201,"Idea")-D15 -> 0 | F15: =COUNTIFS(Catalog!$A$2:$A$201,$A15,Catalog!$F$2:$F$201,"Idea") -> 10 | G15: =D15/10 -> 0 | H15: Journal/planner trend plus genuine emotional utility. | I15: 5k–50k | J15: 50–300 | K15: Pair a Kindle companion to drive discovery.
A16: Caregiver & Medical Logs | B16: Low-Content | C16: Low | D16: =COUNTIFS(Catalog!$A$2:$A$201,$A16,Catalog!$F$2:$F$201,"Published") -> 0 | E16: =10-COUNTIFS(Catalog!$A$2:$A$201,$A16,Catalog!$F$2:$F$201,"Idea")-D16 -> 0 | F16: =COUNTIFS(Catalog!$A$2:$A$201,$A16,Catalog!$F$2:$F$201,"Idea") -> 10 | G16: =D16/10 -> 0 | H16: Medication/symptom trackers for the caregiver & boomer market. | I16: 5k–50k | J16: 50–300 | K16: One clear outcome per book.
A17: Profession-Specific Notebooks & Logs | B17: Low-Content | C17: Low | D17: =COUNTIFS(Catalog!$A$2:$A$201,$A17,Catalog!$F$2:$F$201,"Published") -> 0 | E17: =10-COUNTIFS(Catalog!$A$2:$A$201,$A17,Catalog!$F$2:$F$201,"Idea")-D17 -> 0 | F17: =COUNTIFS(Catalog!$A$2:$A$201,$A17,Catalog!$F$2:$F$201,"Idea") -> 10 | G17: =D17/10 -> 0 | H17: Nurses, truckers, teachers, trades feel 'seen'; hardcover sells at a premium. | I17: 5k–50k | J17: <300 | K17: Try hardcover (~$24.99) for far better royalty.
A18: Recovery & Mental-Health Journals | B18: Low-Content | C18: Low | D18: =COUNTIFS(Catalog!$A$2:$A$201,$A18,Catalog!$F$2:$F$201,"Published") -> 0 | E18: =10-COUNTIFS(Catalog!$A$2:$A$201,$A18,Catalog!$F$2:$F$201,"Idea")-D18 -> 0 | F18: =COUNTIFS(Catalog!$A$2:$A$201,$A18,Catalog!$F$2:$F$201,"Idea") -> 10 | G18: =D18/10 -> 0 | H18: Sobriety trackers, anxiety workbooks, grief journals — steady demand. | I18: 5k–50k | J18: 50–300 | K18: Tie each title to a single outcome.
... A26: Practical AI Guides | B26: Non-Fiction | C26: Medium | D26: =COUNTIFS(Catalog!$A$2:$A$201,$A26,Catalog!$F$2:$F$201,"Published") -> 0 | E26: =10-COUNTIFS(Catalog!$A$2:$A$201,$A26,Catalog!$F$2:$F$201,"Idea")-D26 -> 0 | F26: =COUNTIFS(Catalog!$A$2:$A$201,$A26,Catalog!$F$2:$F$201,"Idea") -> 10 | G26: =D26/10 -> 0 | H26: Demand still ahead of competition; readers want practical, not theory. | I26: Low competition (for now) | J26: <200 | K26: Moves fast — publish quickly, refresh often.
A27: TOTAL | D27: =SUM(D7:D26) -> 0 | E27: =SUM(E7:E26) -> 0 | F27: =SUM(F7:F26) -> 200 | G27: =D27/200 -> 0

Sheet Catalog
A1: Category | B1: Division | C1: Book # | D1: Working Title | E1: Title Strategy | F1: Status | G1: Format | H1: Target Date | I1: ASIN | J1: BSR | K1: Notes
A2: Contemporary & Small-Town Romance | B2: Fiction | C2: 1 | D2: The Second-Chance Bakery on Maple Street | E2: Trope: second-chance + place anchor | F2: Idea
A3: Contemporary & Small-Town Romance | B3: Fiction | C3: 2 | D3: Snowed In with My Enemy | E3: Trope: enemies-to-lovers + forced proximity | F3: Idea
A4: Contemporary & Small-Town Romance | B4: Fiction | C4: 3 | D4: Fake Dating the Fire Chief | E4: Trope: fake dating + swoony hero | F4: Idea
A5: Contemporary & Small-Town Romance | B5: Fiction | C5: 4 | D5: The Inn at Cedar Hollow | E5: Series anchor: cozy place name | F5: Idea
A6: Contemporary & Small-Town Romance | B6: Fiction | C6: 5 | D6: Grumpy Farmer, Sunshine Baker | E6: Trope: grumpy-sunshine | F6: Idea
A7: Contemporary & Small-Town Romance | B7: Fiction | C7: 6 | D7: One More Summer in Willow Bay | E7: Emotional + seasonal place | F7: Idea
A8: Contemporary & Small-Town Romance | B8: Fiction | C8: 7 | D8: The Cowboy's Accidental Bride | E8: Trope: marriage of convenience | F8: Idea
A9: Contemporary & Small-Town Romance | B9: Fiction | C9: 8 | D9: Coming Home to Honeywood | E9: Emotional: homecoming hook | F9: Idea
A10: Contemporary & Small-Town Romance | B10: Fiction | C10: 9 | D10: The Christmas We Almost Missed | E10: Seasonal hook (Q4 sales spike) | F10: Idea
A11: Contemporary & Small-Town Romance | B11: Fiction | C11: 10 | D11: Love Letters from Rosewood Lane | E11: Curiosity + nostalgic imagery | F11: Idea
A12: Romantasy | B12: Fiction | C12: 1 | D12: A Court of Ash and Oath | E12: High-concept series title | F12: Idea
A13: Romantasy | B13: Fiction | C13: 2 | D13: The Dragon's Cursed Bride | E13: Creature hook + cursed trope | F13: Idea
... A201: Practical AI Guides | B201: Non-Fiction | C201: 10 | D201: Prompt Engineering for Everyone: Talk to AI and Get Exactly What You Want | E201: Audience + benefit | F201: Idea

Sheet Guide
A1: How to use this tracker
A3: Workflow
A4: 1. Titles are done | B4: All 200 slots already have a working title and the conversion strategy behind it. Keep, tweak, or swap any of them.
A5: 2. Move it along | B5: Set Status (column F) via the dropdown: Idea → Researching → Drafting → Editing → Cover → Formatting → Published.
A6: 3. Log live data | B6: Once a title is live, add Format, Publish Date, ASIN and BSR to see what's working.
A7: 4. Watch the Dashboard | B7: Per-category Done / In Prog. / To Do and the progress bar recalculate automatically.
A9: What goes in each Catalog column
A10: A–C Category / Division / Book # | B10: Pre-filled — leave as is.
A11: D Working Title | B11: Pre-filled. Specific beats broad; keep the searchable keywords near the front.
A12: E Title Strategy | B12: The conversion lever the title pulls (curiosity, benefit, number, audience, keyword, trope, etc.). Reference it when you write more.
A13: F Status | B13: Dropdown. Only 'Published' counts toward Done on the Dashboard.
A14: G Format | B14: Dropdown: eBook, Paperback, Hardcover, or eBook + Paperback. Hardcover often earns a better royalty on premium logs.
A15: H Target Date | B15: Deadline while drafting; swap to the actual publish date once live.
A16: I ASIN | B16: Amazon's product ID — fill after publishing.
A17: J BSR | B17: Best Seller Rank of your own title — track it over time for momentum.
A18: K Notes | B18: Trim size, cover A/B tests, keyword ideas, series links — anything.
A20: The title strategies used (and why they convert)
A21: Keyword-first | B21: Front-load the exact phrase shoppers type ('Large-Print Sudoku for Seniors'). Wins the Amazon search box before the sale is ever made.
A22: Audience call-out | B22: 'for Beginners', 'for Nurses', 'for Seniors' — the reader instantly self-identifies and feels the book is for them.
A23: Number / quantity | B23: '200 Puzzles', '100 Prompts', '15 Ways' — concrete value and a scannable promise.
A24: Specific outcome / benefit | B24: Name the result: 'Get Your First 100 Sales', 'Sleep Better Tonight'. Sells the transformation, not the object.
A25: Speed / ease | B25: '5-Minute', 'in 30 Days', 'Made Simple' — lowers the effort barrier.
A26: Curiosity / trope hook | B26: Fiction lever: 'The Wife Upstairs Lied', 'Snowed In with My Enemy' signal genre and tension in a glance.
A27: Series / place anchor | B27: Recurring names ('Cedar Hollow', 'Colony Zero') make the Also-Bought engine chain readers from one book to the next.
A29: Redirect readers between your books (cross-sell levers)
A30: Series naming | B30: Titles that share a world/place/number pull buyers down the whole series via Amazon's 'Also Bought' and series page.
A31: Keyword overlap | B31: Books in one niche that share core keywords surface together in search and recommendations, feeding each other traffic.
A32: Kindle + paperback pair | B32: Publish both formats; the cheaper eBook is discovery bait that leads to the print sale and the rest of the catalog.
A33: Back-matter links | B33: End every book with a 'More by this author' page linking your other titles — the single highest-intent ad space you own, and it's free.
A34: Companion pairing | B34: A low-content journal + a Kindle companion (or a fiction novella lead-magnet) cross-promote each other inside the same niche.
A36: Validate a niche before you commit
A37: Best Seller Rank | B37: Top titles around BSR 5,000–50,000 signal steady daily sales without brutal competition.
A38: Review count | B38: Top 5 all at 1,000+ reviews = crowded; 50–300 = proven demand with room to enter.
A39: Price floor | B39: List where royalty is real: roughly $9.99+ paperback, $4.99+ Kindle.
A40: Series > singles | B40: Top earners publish a series within one niche — read-through compounds. That's why this is 10-per-category.
A42: Source & caveat
A43: Where this came from | B43: Categories and demand notes draw on KDP-focused market analyses and Amazon Best Seller Rank data compiled by self-publishing blogs and tools, current as of August 2026 — directional, not an official Amazon list. Titles are original, market-style examples; check each against live listings and avoid duplicating an existing book's exact title before you publish.
